{
  "Name": "QBLP-slcwa_wd20_66_v1_pairs_6",
  "batch_size": 256,
  "dim_transformer_hidden": 1024.0,
  "embedding_dim": 200.0,
  "evaluation_batch_size": 30.0,
  "label_smoothing": 0.15,
  "learning_rate": 0.0017571110732997439,
  "loss": "MarginRankingLoss",
  "max_num_qualifier_pairs": "[6]",
  "model": "QBLP",
  "num_epochs": 70,
  "num_negs_per_pos": 8.0,
  "num_transformer_heads": 2.0,
  "num_transformer_layers": 2.0,
  "test.both.avg.adjusted_mean_rank": 0.26338695348964053,
  "test.both.avg.hits_at_1": 0.016621743036837375,
  "test.both.avg.hits_at_10": 0.09254267744833784,
  "test.both.avg.hits_at_3": 0.03728661275831087,
  "test.both.avg.hits_at_5": 0.05525606469002695,
  "test.both.avg.mean_rank": 866.0350404312668,
  "test.both.avg.mean_reciprocal_rank": 0.04343968745444393,
  "training_approach": "slcwa"
}