{
  "Name": "StarE_wd20_100_v2_pairs_2",
  "attention_drop": 0.4,
  "attention_slope": 0.1,
  "batch_size": 896,
  "composition_function": "models.message_passing_layers.utils.rotate",
  "dim_transformer_hidden": 640.0,
  "embedding_dim": 192.0,
  "evaluation_batch_size": 10.0,
  "feature_dim": 1024.0,
  "gcn_drop": 0.4,
  "hid_drop": 0.1,
  "label_smoothing": 0.1,
  "learning_rate": 0.002784250457508696,
  "loss": "BCEWithLogitsLoss",
  "max_num_qualifier_pairs": "[2]",
  "model": "StarE",
  "num_attention_heads": 2.0,
  "num_epochs": 753,
  "num_layers": 2.0,
  "num_transformer_heads": 2.0,
  "num_transformer_layers": 2.0,
  "qualifier_aggregation": "attn",
  "qualifier_comp_function": "models.message_passing_layers.utils.rotate",
  "restricted_evaluation": true,
  "test.both.avg.adjusted_mean_rank": 0.40596329803920367,
  "test.both.avg.hits_at_1": 0.004457652303120356,
  "test.both.avg.hits_at_10": 0.061664190193164936,
  "test.both.avg.hits_at_3": 0.012630014858841009,
  "test.both.avg.hits_at_5": 0.038632986627043085,
  "test.both.avg.mean_rank": 721.5312035661218,
  "test.both.avg.mean_reciprocal_rank": 0.024336478960594227,
  "triple_qual_weight": 0.8,
  "use_attention": false,
  "use_bias": false,
  "use_learnable_x": false
}